mmpycorex/__init__.py
mmpycorex/_version.py
mmpycorex/core.py
mmpycorex/install.py
mmpycorex/launcher.py
mmpycorex-0.3.16.dist-info/licenses/LICENSE
mmpycorex-0.3.16.dist-info/WHEEL
mmpycorex-0.3.16.dist-info/METADATA
mmpycorex-0.3.16.dist-info/RECORD
