Metadata-Version: 2.4
Name: mmpycorex
Version: 0.3.16
Summary: Python package for unified MMCore access through pymmcore or ZMQ-MMCoreJ + associated utilities
Author-email: Henry Pinkard <henry.pinkard.open.source@gmail.com>
Classifier: License :: OSI Approved :: BSD License
Classifier: Operating System :: OS Independent
License-File: LICENSE
Requires-Dist: pymmcore
Requires-Dist: pyjavaz==1.2.8
Requires-Dist: requests
Requires-Dist: wget
Project-URL: Home, https://github.com/micro-manager/mmpycorex
